rand_warp/__init__.py
rand_warp/warp.py
rand_warp-0.0.1.dist-info/METADATA
rand_warp-0.0.1.dist-info/WHEEL
rand_warp-0.0.1.dist-info/top_level.txt
rand_warp-0.0.1.dist-info/RECORD
